easypki/__init__.py
easypki/build_rsa.py
easypki/build_x509.py
easypki/pki.py
easypki/utils.py
easypki-0.0.1.dist-info/WHEEL
easypki-0.0.1.dist-info/METADATA
easypki-0.0.1.dist-info/RECORD
