Metadata-Version: 2.1
Name: easypki
Version: 0.0.1
Summary: Build a self-signed pki
Home-page: https://github.com/ymrsk/easypki
Author: ymrsk
Requires-Python: >=3.6,<4.0
Classifier: Programming Language :: Python :: 3
Classifier: Programming Language :: Python :: 3.10
Classifier: Programming Language :: Python :: 3.6
Classifier: Programming Language :: Python :: 3.7
Classifier: Programming Language :: Python :: 3.8
Classifier: Programming Language :: Python :: 3.9
Requires-Dist: cryptography (>=37.0.1,<38.0.0)
Requires-Dist: typing-extensions (==4.1)
Project-URL: Repository, https://github.com/ymrsk/easypki
